keyrings/efile/__init__.py
keyrings/efile/encryptedfile.py
keyrings/efile/handler.py
keyrings.efile-3.0.dist-info/LICENSE
keyrings.efile-3.0.dist-info/METADATA
keyrings.efile-3.0.dist-info/WHEEL
keyrings.efile-3.0.dist-info/entry_points.txt
keyrings.efile-3.0.dist-info/top_level.txt
keyrings.efile-3.0.dist-info/RECORD
