Metadata-Version: 2.1
Name: keyrings.efile
Version: 3.0
Summary: Encrypted keyfile without password
Home-page: https://github.com/NMRhub/keyrings.efile.git
Author: Gerard
Author-email: gweatherby@uchc.edu
License: MIT license
Classifier: Programming Language :: Python :: 3.6
Classifier: Programming Language :: Python :: 3.7
Classifier: Programming Language :: Python :: 3.8
Classifier: Programming Language :: Python :: 3.9
Classifier: Programming Language :: Python :: 3.10
Classifier: Programming Language :: Python :: 3.11
Classifier: Programming Language :: Python :: 3.12
License-File: LICENSE
Requires-Dist: filelock
Requires-Dist: keyring
Requires-Dist: properties
Requires-Dist: pycryptodome
